nonebot_plugin_chatGPT_openai/__init__.py
nonebot_plugin_chatGPT_openai/utils.py
nonebot_plugin_chatGPT_openai-0.0.4.dist-info/LICENSE
nonebot_plugin_chatGPT_openai-0.0.4.dist-info/METADATA
nonebot_plugin_chatGPT_openai-0.0.4.dist-info/WHEEL
nonebot_plugin_chatGPT_openai-0.0.4.dist-info/top_level.txt
nonebot_plugin_chatGPT_openai-0.0.4.dist-info/RECORD
