Metadata-Version: 2.1
Name: nonebot-plugin-chatGPT-openai
Version: 0.0.4
Summary: This is a QQ bot on chatGPT3 APT, but it does not support contextual replies.
Home-page: https://github.com/Reversedeer/nonebot_plugin_chatGPT_openai
Author: schwarzwald
Project-URL: Bug Tracker, https://github.com/Reversedeer/nonebot_plugin_chatGPT_openai/issues
Classifier: Programming Language :: Python :: 3
Classifier: License :: OSI Approved :: GNU General Public License v3 (GPLv3)
Classifier: Operating System :: OS Independent
Requires-Python: >=3.7
License-File: LICENSE
Requires-Dist: nonebot-adapter-onebot (>=2.0.0-beta.1)
Requires-Dist: nonebot2 (>=2.0.0-beta.1)
